starformation/__init__.py
starformation/formation.py
starformation/star.py
starformation/classic/__init__.py
starformation/classic/cstar.py
starformation/classic/yfstar.py
starformation-0.0.3.dist-info/LICENSE
starformation-0.0.3.dist-info/METADATA
starformation-0.0.3.dist-info/WHEEL
starformation-0.0.3.dist-info/top_level.txt
starformation-0.0.3.dist-info/RECORD
