Metadata-Version: 2.1
Name: starformation
Version: 0.0.3
Summary: Star Formation is a Python library to quickly develop clean modular models/pipelines.
Home-page: https://github.com/TommyDong1998/StarFormation
Author: Tommy Dong
Author-email: tommydong1998@gmail.com
License: UNKNOWN
Platform: UNKNOWN
Requires-Dist: backtrader
Requires-Dist: pathos
